odoo/addons/invader_payment_sips/README.rst
odoo/addons/invader_payment_sips/__init__.py
odoo/addons/invader_payment_sips/__manifest__.py
odoo/addons/invader_payment_sips/i18n/invader_payment_sips.pot
odoo/addons/invader_payment_sips/readme/CONTRIBUTORS.rst
odoo/addons/invader_payment_sips/readme/DESCRIPTION.rst
odoo/addons/invader_payment_sips/services/__init__.py
odoo/addons/invader_payment_sips/services/payment_sips.py
odoo/addons/invader_payment_sips/static/description/index.html
odoo13_addon_invader_payment_sips-13.0.1.1.0.dist-info/METADATA
odoo13_addon_invader_payment_sips-13.0.1.1.0.dist-info/WHEEL
odoo13_addon_invader_payment_sips-13.0.1.1.0.dist-info/top_level.txt
odoo13_addon_invader_payment_sips-13.0.1.1.0.dist-info/RECORD
