Metadata-Version: 2.1
Name: odoo13-addon-invader-payment-sips
Version: 13.0.1.1.0
Summary: REST Services for Worldline SIPS Payments (base module)
Home-page: https://github.com/shopinvader/odoo-shopinvader-payment
Author: ACSONE SA/NV
License: AGPL-3
Platform: UNKNOWN
Classifier: Programming Language :: Python
Classifier: Framework :: Odoo
Classifier: License :: OSI Approved :: GNU Affero General Public License v3
Requires-Python: >=3.5
Requires-Dist: cerberus
Requires-Dist: odoo13-addon-base-rest
Requires-Dist: odoo13-addon-invader-payment
Requires-Dist: odoo (<13.1dev,>=13.0a)
